rolumns/VERSION
rolumns/__init__.py
rolumns/by_key.py
rolumns/by_path.py
rolumns/by_user_defined_fields.py
rolumns/column.py
rolumns/columns.py
rolumns/cursor.py
rolumns/data_resolver.py
rolumns/group.py
rolumns/logging.py
rolumns/py.typed
rolumns/source.py
rolumns/translation_state.py
rolumns/types.py
rolumns/enums/__init__.py
rolumns/enums/column_alignment.py
rolumns/enums/py.typed
rolumns/exceptions/__init__.py
rolumns/exceptions/multiple_groups.py
rolumns/exceptions/py.typed
rolumns/exceptions/translation_failed.py
rolumns/exceptions/udf_multiple_values.py
rolumns/renderers/__init__.py
rolumns/renderers/markdown.py
rolumns/renderers/py.typed
rolumns/renderers/rows.py
rolumns-1.4.1.dist-info/LICENSE
rolumns-1.4.1.dist-info/METADATA
rolumns-1.4.1.dist-info/WHEEL
rolumns-1.4.1.dist-info/top_level.txt
rolumns-1.4.1.dist-info/RECORD
